azureml/__init__.py
azureml/errors.py
azureml/http.py
azureml/serialization.py
azureml/services.py
azureml-0.2.6.dist-info/DESCRIPTION.rst
azureml-0.2.6.dist-info/METADATA
azureml-0.2.6.dist-info/RECORD
azureml-0.2.6.dist-info/WHEEL
azureml-0.2.6.dist-info/metadata.json
azureml-0.2.6.dist-info/top_level.txt
